DESCRIPTION.rst
LICENSE
MANIFEST.in
README.md
setup.py
oide_nb_term.egg-info/PKG-INFO
oide_nb_term.egg-info/SOURCES.txt
oide_nb_term.egg-info/dependency_links.txt
oide_nb_term.egg-info/not-zip-safe
oide_nb_term.egg-info/requires.txt
oide_nb_term.egg-info/top_level.txt
oidenbterm/.bowerrc
oidenbterm/__init__.py
oidenbterm/bower.json
oidenbterm/handlers.py
oidenbterm/settings.py
oidenbterm/urls.py
oidenbterm/mixins/__init__.py
oidenbterm/mixins/kernel_mixin.py
oidenbterm/static/nbnotebook.directive.js
oidenbterm/static/nbterm.css
oidenbterm/static/nbterm.html
oidenbterm/static/nbterm.js
oidenbterm/static/notebook.controller.js
oidenbterm/static/notebook.service.js
oidenbterm/static/terminal.controller.js
oidenbterm/static/bower_components/angular/angular-csp.css
oidenbterm/static/bower_components/angular/angular.js
oidenbterm/static/bower_components/angular/angular.min.js
oidenbterm/static/bower_components/angular/index.js
oidenbterm/static/bower_components/angular-marked/gruntfile.js
oidenbterm/static/bower_components/angular-marked/karma.conf.js
oidenbterm/static/bower_components/angular-marked/dist/angular-marked.js
oidenbterm/static/bower_components/angular-marked/dist/angular-marked.min.js
oidenbterm/static/bower_components/angular-marked/lib/angular-marked.js
oidenbterm/static/bower_components/marked/Gulpfile.js
oidenbterm/static/bower_components/marked/index.js
oidenbterm/static/bower_components/marked/marked.min.js
oidenbterm/static/bower_components/marked/lib/marked.js
oidenbterm/static/templates/nb-cell-code.html
oidenbterm/static/templates/nb-cell-markdown.html
oidenbterm/static/templates/nb-notebook.html
oidenbterm/static/templates/notebook.html
oidenbterm/static/templates/open-modal.html
oidenbterm/static/templates/saveas-modal.html
oidenbterm/static/templates/terminal.html