Metadata-Version: 1.1
Name: oide-nb-term
Version: 0.1.1
Summary: Online Integrated Development Environment (OIDE) - NBTerm
Home-page: https://github.com/ResearchComputing/oide-nb-term
Author: Zebula Sampedro
Author-email: sampedro@colorado.edu
License: MIT, see LICENSE
Platform: UNKNOWN
Classifier: Development Status :: 3 - Alpha
Classifier: Intended Audience :: Developers
Classifier: Natural Language :: English
Classifier: Operating System :: Unix
Classifier: Topic :: Software Development :: User Interfaces
Classifier: Topic :: Software Development :: Build Tools
Classifier: Topic :: Text Editors :: Integrated Development Environments (IDE)
Classifier: Topic :: Terminals :: Terminal Emulators/X Terminals
Classifier: License :: OSI Approved :: MIT License
Classifier: Programming Language :: Python :: 2.7
Classifier: Programming Language :: JavaScript
